earthformer/__init__.py
earthformer/common.py
earthformer/config.py
earthformer/earthformer.py
earthformer/train_cuboid_earthnet.py
earthformer/baselines/__init__.py
earthformer/baselines/persistence.py
earthformer/cuboid_transformer/__init__.py
earthformer/cuboid_transformer/cuboid_transformer.py
earthformer/cuboid_transformer/cuboid_transformer_patterns.py
earthformer/cuboid_transformer/cuboid_transformer_unet_dec.py
earthformer/cuboid_transformer/utils.py
earthformer/datasets/__init__.py
earthformer/datasets/augmentation.py
earthformer/datasets/earthnet/__init__.py
earthformer/datasets/earthnet/earthnet21x_dataloader.py
earthformer/datasets/earthnet/earthnet_dataloader.py
earthformer/datasets/earthnet/earthnet_scores.py
earthformer/datasets/earthnet/visualization.py
earthformer/datasets/earthnet/earthnet_toolkit/__init__.py
earthformer/datasets/earthnet/earthnet_toolkit/coords.py
earthformer/datasets/earthnet/earthnet_toolkit/coords_dict.py
earthformer/datasets/earthnet/earthnet_toolkit/download.py
earthformer/datasets/earthnet/earthnet_toolkit/download_links.py
earthformer/datasets/earthnet/earthnet_toolkit/parallel_score.py
earthformer/datasets/earthnet/earthnet_toolkit/plot_cube.py
earthformer/datasets/enso/__init__.py
earthformer/datasets/enso/enso_dataloader.py
earthformer/datasets/moving_mnist/__init__.py
earthformer/datasets/moving_mnist/moving_mnist.py
earthformer/datasets/nbody/__init__.py
earthformer/datasets/nbody/nbody_mnist.py
earthformer/datasets/nbody/nbody_mnist_torch_wrap.py
earthformer/datasets/sevir/__init__.py
earthformer/datasets/sevir/sevir_dataloader.py
earthformer/datasets/sevir/sevir_torch_wrap.py
earthformer/metrics/__init__.py
earthformer/metrics/enso.py
earthformer/metrics/sevir.py
earthformer/metrics/skill_scores.py
earthformer/metrics/torchmetrics_wo_compute.py
earthformer/scripts/baselines/persistence/earthnet/README.md
earthformer/scripts/baselines/persistence/earthnet/cfg.yaml
earthformer-0.2.1.dist-info/LICENSE
earthformer-0.2.1.dist-info/METADATA
earthformer-0.2.1.dist-info/WHEEL
earthformer-0.2.1.dist-info/dependency_links.txt
earthformer-0.2.1.dist-info/top_level.txt
earthformer-0.2.1.dist-info/RECORD
