Metadata-Version: 2.1
Name: earthformer
Version: 0.2.1
Summary: A Python package for Earth forecasting transformer (Earthformer)
Home-page: https://github.com/opengeos/earthformer
Author: Qiusheng Wu
Author-email: giswqs@gmail.com
License: Apache Software License 2.0
Keywords: earthformer
Classifier: Intended Audience :: Developers
Classifier: License :: OSI Approved :: Apache Software License
Classifier: Natural Language :: English
Classifier: Programming Language :: Python :: 3
Classifier: Programming Language :: Python :: 3.8
Classifier: Programming Language :: Python :: 3.9
Classifier: Programming Language :: Python :: 3.10
Classifier: Programming Language :: Python :: 3.11
Requires-Python: >=3.8
License-File: LICENSE
Requires-Dist: boto3
Requires-Dist: h5py >=2.10.0
Requires-Dist: scipy
Requires-Dist: tqdm
Requires-Dist: regex
Requires-Dist: requests
Requires-Dist: transformers >=4.3.0
Requires-Dist: pandas
Requires-Dist: einops >=0.3.0
Requires-Dist: tensorboard
Requires-Dist: omegaconf
Requires-Dist: matplotlib
Requires-Dist: botocore
Requires-Dist: earthnet
Requires-Dist: leafmap
Requires-Dist: torchmetrics <1.0.0
